napari_n2v/__init__.py
napari_n2v/_predict_widget.py
napari_n2v/_sample_data.py
napari_n2v/_train_widget.py
napari_n2v/napari.yaml
napari_n2v/_tests/__init__.py
napari_n2v/_tests/test_axes_widget.py
napari_n2v/_tests/test_expert_settings.py
napari_n2v/_tests/test_io_utils.py
napari_n2v/_tests/test_load_images_utils.py
napari_n2v/_tests/test_n2v_utils.py
napari_n2v/_tests/test_prediction_worker.py
napari_n2v/_tests/test_resources.py
napari_n2v/_tests/test_training_worker.py
napari_n2v/_tests/test_utils.py
napari_n2v/examples/__init__.py
napari_n2v/examples/structN2V.py
napari_n2v/resources/GitHub-Mark-Light-32px.png
napari_n2v/resources/TF_White_Icon.png
napari_n2v/resources/TF_legal_mention.txt
napari_n2v/resources/__init__.py
napari_n2v/resources/gear_16.png
napari_n2v/resources/juglab_logo_128.png
napari_n2v/resources/resources.py
napari_n2v/utils/__init__.py
napari_n2v/utils/expert_settings.py
napari_n2v/utils/io_utils.py
napari_n2v/utils/load_images_utils.py
napari_n2v/utils/loading_worker.py
napari_n2v/utils/n2v_utils.py
napari_n2v/utils/prediction_worker.py
napari_n2v/utils/training_worker.py
napari_n2v/widgets/__init__.py
napari_n2v/widgets/axes_widget.py
napari_n2v/widgets/banner_widget.py
napari_n2v/widgets/expert_settings_widget.py
napari_n2v/widgets/folder_widget.py
napari_n2v/widgets/gpu_widget.py
napari_n2v/widgets/magicgui_widgets.py
napari_n2v/widgets/qt_widgets.py
napari_n2v/widgets/scroll_wrapper.py
napari_n2v/widgets/tbplot_widget.py
napari_n2v-0.1.1.dist-info/LICENSE
napari_n2v-0.1.1.dist-info/METADATA
napari_n2v-0.1.1.dist-info/WHEEL
napari_n2v-0.1.1.dist-info/entry_points.txt
napari_n2v-0.1.1.dist-info/top_level.txt
napari_n2v-0.1.1.dist-info/RECORD
