Metadata-Version: 2.1
Name: napari-n2v
Version: 0.1.1
Summary: A self-supervised denoising algorithm now usable by all in napari.
Home-page: https://github.com/juglab/napari-n2v
Author: Tom Burke, Joran Deschamps
Author-email: joran.deschamps@fht.org
License: BSD-3-Clause
Project-URL: Bug Tracker, https://github.com/juglab/napari-n2v/issues
Project-URL: Documentation, https://juglab.github.io/napari-n2v/
Project-URL: Source Code, https://github.com/juglab/napari-n2v
Project-URL: User Support, https://github.com/juglab/napari-n2v/issues
Classifier: Framework :: napari
Classifier: Development Status :: 4 - Beta
Classifier: Intended Audience :: Science/Research
Classifier: Topic :: Scientific/Engineering :: Image Processing
Classifier: Topic :: Scientific/Engineering :: Information Analysis
Classifier: Programming Language :: Python
Classifier: Programming Language :: Python :: 3.8
Classifier: Programming Language :: Python :: 3.9
Classifier: Programming Language :: Python :: 3.10
Classifier: Operating System :: OS Independent
Classifier: License :: OSI Approved :: BSD License
Requires-Python: >=3.8
License-File: LICENSE
Requires-Dist: scikit-image
Requires-Dist: bioimageio.core
Requires-Dist: n2v >=0.3.2
Requires-Dist: napari-time-slicer >=0.4.9
Requires-Dist: napari
Requires-Dist: qtpy
Requires-Dist: pyqtgraph
Requires-Dist: tensorflow >=2.10.0 ; platform_system != "Darwin" or platform_machine != "arm64"
Requires-Dist: tensorflow-macos ; platform_system == "Darwin" and platform_machine == "arm64"
Requires-Dist: tensorflow-metal ; platform_system == "Darwin" and platform_machine == "arm64"
Requires-Dist: numpy <1.24.0 ; python_version < "3.9"
Requires-Dist: numpy ; python_version >= "3.9"
Provides-Extra: testing
Requires-Dist: pytest ; extra == 'testing'
Requires-Dist: pytest-cov ; extra == 'testing'
Requires-Dist: pytest-qt ; extra == 'testing'
Requires-Dist: pyqt5 ; extra == 'testing'
